briefcase/__init__.py
briefcase_ai-0.1.0.dist-info/licenses/LICENSE
briefcase_ai-0.1.0.dist-info/licenses/LICENSE-OVERVIEW.md
enterprise/__init__.py
enterprise/config_example.py
enterprise/extensions.py
enterprise/analytics/__init__.py
enterprise/analytics/dashboards.py
enterprise/analytics/insights.py
enterprise/analytics/metrics.py
enterprise/auth/__init__.py
enterprise/auth/rbac.py
enterprise/auth/sso.py
enterprise/compliance/__init__.py
enterprise/compliance/audit.py
enterprise/compliance/reporting.py
enterprise/compliance/retention.py
enterprise/hosted/__init__.py
enterprise/hosted/replay_service.py
enterprise/hosted/scaling.py
enterprise/hosted/tenant.py
oss/__init__.py
oss/cli.py
oss/api/__init__.py
oss/api/app.py
oss/api/auth.py
oss/api/websocket.py
oss/api/routers/__init__.py
oss/api/routers/policies.py
oss/api/routers/replay.py
oss/api/routers/snapshots.py
oss/cli/__init__.py
oss/replay/__init__.py
oss/replay/diff.py
oss/replay/engine.py
oss/replay/orchestrator.py
oss/replay/policies.py
oss/sdk/__init__.py
oss/sdk/capture.py
oss/sdk/client.py
oss/sdk/fixtures.py
oss/sdk/models.py
oss/sdk/schema.py
oss/sdk/serialization.py
oss/storage/__init__.py
oss/storage/artifacts.py
oss/storage/cli.py
oss/storage/compression.py
oss/storage/config.py
oss/storage/database.py
oss/storage/encryption.py
oss/storage/management.py
oss/storage/models.py
oss/storage/repository.py
oss/storage/snapshot_repository.py
oss/storage/test_storage.py
briefcase_ai-0.1.0.dist-info/METADATA
briefcase_ai-0.1.0.dist-info/WHEEL
briefcase_ai-0.1.0.dist-info/entry_points.txt
briefcase_ai-0.1.0.dist-info/top_level.txt
briefcase_ai-0.1.0.dist-info/RECORD
