Metadata-Version: 2.4
Name: briefcase-ai
Version: 0.1.0
Summary: Deterministic observability & replay for AI systems
Author: briefcase-ai Contributors
License: MIT
Requires-Python: >=3.9
License-File: LICENSE
License-File: LICENSE-OVERVIEW.md
Requires-Dist: pydantic>=2.0.0
Requires-Dist: fastapi>=0.100.0
Requires-Dist: uvicorn>=0.23.0
Requires-Dist: sqlalchemy>=2.0.0
Requires-Dist: alembic>=1.11.0
Requires-Dist: httpx>=0.24.0
Requires-Dist: click>=8.1.0
Requires-Dist: python-multipart>=0.0.6
Requires-Dist: websockets>=11.0.0
Requires-Dist: aiofiles>=23.0.0
Requires-Dist: python-jose[cryptography]>=3.3.0
Requires-Dist: passlib[bcrypt]>=1.7.4
Requires-Dist: email-validator>=2.0.0
Requires-Dist: lz4>=4.0.0
Requires-Dist: cryptography>=41.0.0
Provides-Extra: dev
Requires-Dist: pytest>=7.0.0; extra == "dev"
Requires-Dist: pytest-asyncio>=0.21.0; extra == "dev"
Requires-Dist: pytest-cov>=4.0.0; extra == "dev"
Requires-Dist: black>=23.0.0; extra == "dev"
Requires-Dist: mypy>=1.0.0; extra == "dev"
Requires-Dist: ruff>=0.0.270; extra == "dev"
Provides-Extra: enterprise
Requires-Dist: python-saml>=1.15.0; extra == "enterprise"
Requires-Dist: ldap3>=2.9.0; extra == "enterprise"
Dynamic: author
Dynamic: license
Dynamic: license-file
Dynamic: provides-extra
Dynamic: requires-dist
Dynamic: requires-python
Dynamic: summary
